MANIFEST.in
README.rst
admin.ini
cached_version.json
setup.cfg
setup.py
nozama/__init__.py
nozama/cloudsearch/__init__.py
nozama/cloudsearch/client/__init__.py
nozama/cloudsearch/client/rest.py
nozama/cloudsearch/client/admintool/__init__.py
nozama/cloudsearch/client/admintool/admincmds.py
nozama/cloudsearch/client/admintool/main.py
nozama/cloudsearch/client/tests/README.txt
nozama/cloudsearch/client/tests/__init__.py
nozama_cloudsearch_client.egg-info/PKG-INFO
nozama_cloudsearch_client.egg-info/SOURCES.txt
nozama_cloudsearch_client.egg-info/dependency_links.txt
nozama_cloudsearch_client.egg-info/eager_resources.txt
nozama_cloudsearch_client.egg-info/entry_points.txt
nozama_cloudsearch_client.egg-info/namespace_packages.txt
nozama_cloudsearch_client.egg-info/not-zip-safe
nozama_cloudsearch_client.egg-info/requires.txt
nozama_cloudsearch_client.egg-info/top_level.txt