Metadata-Version: 1.0
Name: nozama-cloudsearch-client
Version: 1.0.3
Summary: The Python REST client library to talk to the nozama-cloudsearch service.The implements the Amazon CloudSearch and Nozama's testing helper API.
Home-page: https://github.com/oisinmulvihill/nozama-cloudsearch
Author: Oisin Mulvihill
Author-email: oisin dot mulvihill a-t  gmail dot com
License: BSD
Platform: UNKNOWN
Classifier: Programming Language :: Python
